{
  "crawler": {
    "id": "at_en-burg-kino",
    "is_booking_link_capable": false,
    "crawl-e": {
      "version": "0.6.5"
    }
  },
  "cinema": {
    "name": "Burg Kino",
    "address": "Opernring 191010 Vienna, Austria",
    "website": "https://www.burgkino.at",
    "phone": "+43 1 587 84 06"
  },
  "showtimes": [
    {
      "movie_title": "Asteroid City",
      "start_at": "2023-07-05T20:30:00",
      "is_3d": false
    },
    {
      "movie_title": "Asteroid City",
      "start_at": "2023-07-05T22:30:00",
      "is_3d": false
    },
    {
      "movie_title": "Asteroid City",
      "start_at": "2023-07-05T22:30:00",
      "is_3d": false
    },
    {
      "movie_title": "Asteroid City",
      "start_at": "2023-07-07T00:30:00",
      "is_3d": false
    },
    {
      "movie_title": "Asteroid City",
      "start_at": "2023-07-06T20:30:00",
      "is_3d": false
    },
    {
      "movie_title": "Asteroid City",
      "start_at": "2023-07-06T22:30:00",
      "is_3d": false
    },
    {
      "movie_title": "Asteroid City",
      "start_at": "2023-07-06T22:30:00",
      "is_3d": false
    },
    {
      "movie_title": "Asteroid City",
      "start_at": "2023-07-08T00:30:00",
      "is_3d": false
    },
    {
      "movie_title": "Asteroid City",
      "start_at": "2023-07-07T20:30:00",
      "is_3d": false
    },
    {
      "movie_title": "Asteroid City",
      "start_at": "2023-07-07T22:30:00",
      "is_3d": false
    },
    {
      "movie_title": "Asteroid City",
      "start_at": "2023-07-07T22:30:00",
      "is_3d": false
    },
    {
      "movie_title": "Asteroid City",
      "start_at": "2023-07-09T00:30:00",
      "is_3d": false
    },
    {
      "movie_title": "Asteroid City",
      "start_at": "2023-07-08T20:30:00",
      "is_3d": false
    },
    {
      "movie_title": "Asteroid City",
      "start_at": "2023-07-08T22:30:00",
      "is_3d": false
    },
    {
      "movie_title": "Asteroid City",
      "start_at": "2023-07-08T22:30:00",
      "is_3d": false
    },
    {
      "movie_title": "Asteroid City",
      "start_at": "2023-07-10T00:30:00",
      "is_3d": false
    },
    {
      "movie_title": "Asteroid City",
      "start_at": "2023-07-09T20:30:00",
      "is_3d": false
    },
    {
      "movie_title": "Asteroid City",
      "start_at": "2023-07-09T22:30:00",
      "is_3d": false
    },
    {
      "movie_title": "Asteroid City",
      "start_at": "2023-07-09T22:30:00",
      "is_3d": false
    },
    {
      "movie_title": "Asteroid City",
      "start_at": "2023-07-11T00:30:00",
      "is_3d": false
    },
    {
      "movie_title": "Asteroid City",
      "start_at": "2023-07-10T20:30:00",
      "is_3d": false
    },
    {
      "movie_title": "Asteroid City",
      "start_at": "2023-07-10T22:30:00",
      "is_3d": false
    },
    {
      "movie_title": "Asteroid City",
      "start_at": "2023-07-10T22:30:00",
      "is_3d": false
    },
    {
      "movie_title": "Asteroid City",
      "start_at": "2023-07-12T00:30:00",
      "is_3d": false
    },
    {
      "movie_title": "Asteroid City",
      "start_at": "2023-07-11T20:30:00",
      "is_3d": false
    },
    {
      "movie_title": "Asteroid City",
      "start_at": "2023-07-11T22:30:00",
      "is_3d": false
    },
    {
      "movie_title": "Asteroid City",
      "start_at": "2023-07-11T22:30:00",
      "is_3d": false
    },
    {
      "movie_title": "Asteroid City",
      "start_at": "2023-07-13T00:30:00",
      "is_3d": false
    },
    {
      "movie_title": "Asteroid City",
      "start_at": "2023-07-12T20:30:00",
      "is_3d": false
    },
    {
      "movie_title": "Asteroid City",
      "start_at": "2023-07-12T22:30:00",
      "is_3d": false
    },
    {
      "movie_title": "Asteroid City",
      "start_at": "2023-07-12T22:30:00",
      "is_3d": false
    },
    {
      "movie_title": "Asteroid City",
      "start_at": "2023-07-14T00:30:00",
      "is_3d": false
    },
    {
      "movie_title": "Asteroid City",
      "start_at": "2023-07-13T20:30:00",
      "is_3d": false
    },
    {
      "movie_title": "Asteroid City",
      "start_at": "2023-07-13T22:30:00",
      "is_3d": false
    },
    {
      "movie_title": "Asteroid City",
      "start_at": "2023-07-13T22:30:00",
      "is_3d": false
    },
    {
      "movie_title": "Asteroid City",
      "start_at": "2023-07-15T00:30:00",
      "is_3d": false
    },
    {
      "movie_title": "Double Feature",
      "start_at": "2023-07-05T22:45:00",
      "is_3d": false
    },
    {
      "movie_title": "Double Feature",
      "start_at": "2023-07-07T00:45:00",
      "is_3d": false
    },
    {
      "movie_title": "Double Feature",
      "start_at": "2023-07-07T20:15:00",
      "is_3d": false
    },
    {
      "movie_title": "Double Feature",
      "start_at": "2023-07-07T22:15:00",
      "is_3d": false
    }
  ]
}